payos_lib_python/__init__.py
payos_lib_python/constants.py
payos_lib_python/custom_error.py
payos_lib_python/index.py
payos_lib_python/type.py
payos_lib_python/utils.py
payos_lib_python-0.1.6.dist-info/METADATA
payos_lib_python-0.1.6.dist-info/WHEEL
payos_lib_python-0.1.6.dist-info/top_level.txt
payos_lib_python-0.1.6.dist-info/RECORD
