Metadata-Version: 2.1
Name: payos-lib-python
Version: 0.1.6
Summary: A library for create Payment Link of PayOS and more
Author: Casso
Author-email: tranglq@casso.vn
Keywords: payos,vietqrpro,payos-python
Classifier: Programming Language :: Python :: 3
Requires-Python: >=3.6
Requires-Dist: requests
